README.md
setup.cfg
setup.py
jsonene/__init__.py
jsonene/constraints.py
jsonene/exceptions.py
jsonene/factories.py
jsonene/fields.py
jsonene/operators.py
jsonene.egg-info/PKG-INFO
jsonene.egg-info/SOURCES.txt
jsonene.egg-info/dependency_links.txt
jsonene.egg-info/requires.txt
jsonene.egg-info/top_level.txt