Metadata-Version: 2.1
Name: jsonene
Version: 0.1.0
Summary: Type declaration and validation library for JSON
Home-page: https://github.com/nikhil-rupanawar/jsonene
Author: Nikhil Rupanawar
Author-email: conikhil@gmail.com
License: MIT
Keywords: json,validation,schema
Platform: UNKNOWN
Classifier: Programming Language :: Python :: 3
Classifier: License :: OSI Approved :: MIT License
Classifier: Operating System :: OS Independent
Requires-Python: >=3.6
